taxonomyresolver/__init__.py
taxonomyresolver/cli.py
taxonomyresolver/library.py
taxonomyresolver/tree.py
taxonomyresolver/utils.py
taxonomy_resolver-1.1.0.dist-info/LICENSE
taxonomy_resolver-1.1.0.dist-info/METADATA
taxonomy_resolver-1.1.0.dist-info/WHEEL
taxonomy_resolver-1.1.0.dist-info/entry_points.txt
taxonomy_resolver-1.1.0.dist-info/RECORD
