Metadata-Version: 2.3
Name: taxonomy-resolver
Version: 1.1.0
Summary: Taxonomy Resolver builds NCBI Taxonomy Trees and lists of Taxonomy Identifiers (TaxIDs) based on the NCBI Taxonomy Database
License: Apache-2.0
Author: Fábio Madeira
Author-email: fmadeira@ebi.ac.uk
Requires-Python: >=3.10,<4.0
Classifier: Development Status :: 4 - Beta
Classifier: Intended Audience :: Developers
Classifier: Intended Audience :: Science/Research
Classifier: License :: OSI Approved :: Apache Software License
Classifier: Natural Language :: English
Classifier: Programming Language :: Python :: 3
Classifier: Programming Language :: Python :: 3.10
Classifier: Programming Language :: Python :: 3.11
Classifier: Programming Language :: Python :: 3.12
Classifier: Programming Language :: Python :: 3.13
Classifier: Programming Language :: Python :: Implementation :: PyPy
Classifier: Topic :: Internet
Classifier: Topic :: Scientific/Engineering :: Bio-Informatics
Classifier: Topic :: Software Development :: Libraries :: Python Modules
Requires-Dist: click (>=8.1.7)
Requires-Dist: pandas (>=2.2.2)
Requires-Dist: pytest (>=8.2.1)
Requires-Dist: requests (>=2.32.2)
Requires-Dist: tqdm (>4.65.0)
